{
	"configurations" : 
	[
		{
			"directories" : 
			[
				{
					"build" : ".",
					"hasInstallRule" : true,
					"jsonFile" : "directory-.-e3efea9b0ba0bd7731c8.json",
					"minimumCMakeVersion" : 
					{
						"string" : "3.12"
					},
					"projectIndex" : 0,
					"source" : ".",
					"targetIndexes" : 
					[
						0,
						1,
						2,
						3
					]
				}
			],
			"name" : "",
			"projects" : 
			[
				{
					"directoryIndexes" : 
					[
						0
					],
					"name" : "cpp_subcontroller",
					"targetIndexes" : 
					[
						0,
						1,
						2,
						3
					]
				}
			],
			"targets" : 
			[
				{
					"directoryIndex" : 0,
					"id" : "cpp_subcontroller_uninstall::@6890427a1f51a3e7e1df",
					"jsonFile" : "target-cpp_subcontroller_uninstall-3ad718d2263a033d9da3.json",
					"name" : "cpp_subcontroller_uninstall",
					"projectIndex" : 0
				},
				{
					"directoryIndex" : 0,
					"id" : "motion_director::@6890427a1f51a3e7e1df",
					"jsonFile" : "target-motion_director-332c6122d2a048375d24.json",
					"name" : "motion_director",
					"projectIndex" : 0
				},
				{
					"directoryIndex" : 0,
					"id" : "navigator::@6890427a1f51a3e7e1df",
					"jsonFile" : "target-navigator-d940c67f15261996eda1.json",
					"name" : "navigator",
					"projectIndex" : 0
				},
				{
					"directoryIndex" : 0,
					"id" : "uninstall::@6890427a1f51a3e7e1df",
					"jsonFile" : "target-uninstall-67f3ba68a52a153a95ed.json",
					"name" : "uninstall",
					"projectIndex" : 0
				}
			]
		}
	],
	"kind" : "codemodel",
	"paths" : 
	{
		"build" : "/home/robocatsorin/Desktop/RobotCode2025/ros2_ws/build/cpp_subcontroller",
		"source" : "/home/robocatsorin/Desktop/RobotCode2025/ros2_ws/src/cpp_subcontroller"
	},
	"version" : 
	{
		"major" : 2,
		"minor" : 8
	}
}
